setup.py
jwt_flask_auth/__init__.py
jwt_flask_auth/auth.py
jwt_flask_auth.egg-info/PKG-INFO
jwt_flask_auth.egg-info/SOURCES.txt
jwt_flask_auth.egg-info/dependency_links.txt
jwt_flask_auth.egg-info/top_level.txt