Metadata-Version: 2.1
Name: jwt-flask-auth
Version: 0.0.1
Summary: Provide an  easy way to handle authentication(login with jwt generated, token required decorator) in flask applications
Author: Eteil Junior Djoumatchoua
